custom_action/__init__.py
tests/__init__.py
tests/test_custom_action.py
custom_actions-0.0.1.dist-info/LICENSE
custom_actions-0.0.1.dist-info/METADATA
custom_actions-0.0.1.dist-info/WHEEL
custom_actions-0.0.1.dist-info/top_level.txt
custom_actions-0.0.1.dist-info/RECORD
